dsp_ifsc/__init__.py
dsp_ifsc/sequence.py
dsp_ifsc/signal.py
dsp_ifsc/system.py
dsp_ifsc-0.0.14.dist-info/LICENSE
dsp_ifsc-0.0.14.dist-info/METADATA
dsp_ifsc-0.0.14.dist-info/WHEEL
dsp_ifsc-0.0.14.dist-info/RECORD
