Metadata-Version: 2.1
Name: dsp-ifsc
Version: 0.0.14
Summary: A small package with some utilities for DSP grade at IFSC - Campus Florianópolis
Home-page: https://github.com/JoaoMario109/ifsc-dsp-2024
License: MIT
Author: João Mário Lago
Author-email: joao.mcil2003@aluno.ifsc.edu.br
Requires-Python: >=3.8
Classifier: License :: OSI Approved :: MIT License
Classifier: Operating System :: OS Independent
Classifier: Programming Language :: Python :: 3
Classifier: Programming Language :: Python :: 3.8
Classifier: Programming Language :: Python :: 3.9
Classifier: Programming Language :: Python :: 3.10
Classifier: Programming Language :: Python :: 3.11
Classifier: Programming Language :: Python :: 3.12
Requires-Dist: matplotlib
Requires-Dist: numpy
Project-URL: Issues, https://github.com/JoaoMario109/ifsc-dsp-2024/issues
Project-URL: Repository, https://github.com/JoaoMario109/ifsc-dsp-2024
